{"default":{"identifier":"default","description":"enables the default permissions","local":true,"windows":["main"],"permissions":["path:default","event:default","window:default","webview:default","app:default","resources:default","image:default","menu:default","tray:default"]},"desktop":{"identifier":"desktop","description":"enables the default permissions","local":true,"windows":["main"],"permissions":["window:default","webview:allow-create-webview-window","window:allow-start-dragging","window:allow-center","window:allow-destroy","window:allow-close","window:allow-hide","window:allow-minimize","window:allow-maximize","window:allow-toggle-maximize","window:allow-set-fullscreen","tray:allow-new","tray:allow-set-icon","tray:allow-set-menu","tray:allow-set-tooltip","tray:allow-set-title","tray:allow-set-visible","tray:allow-set-temp-dir-path","tray:allow-set-icon-as-template","os:allow-arch","os:allow-exe-extension","os:allow-family","os:allow-hostname","os:allow-locale","os:allow-platform","os:allow-os-type","os:allow-version",{"identifier":"http:allow-fetch","allow":[{"url":"https://*"}]},{"identifier":"http:default","allow":[{"url":"https://*"}]}]}}